{"asin": "B07CWWD6H9", "name": "Google Pixel 2 128GB 5\" 12MP SIM-Free Smartphone in Just Black", "ratings": [5, 5, 5, 2], "aspect_to_sentiments": {"overall": {"POSITIVE": 1, "NEUTRAL": 0, "NEGATIVE": 0}, "battery": {"POSITIVE": 0, "NEUTRAL": 0, "NEGATIVE": 0}, "camera": {"POSITIVE": 0, "NEUTRAL": 0, "NEGATIVE": 0}, "screen": {"POSITIVE": 0, "NEUTRAL": 0, "NEGATIVE": 5}, "value for price": {"POSITIVE": 0, "NEUTRAL": 0, "NEGATIVE": 0}, "service & warranty": {"POSITIVE": 0, "NEUTRAL": 0, "NEGATIVE": 1}, "brand & os": {"POSITIVE": 2, "NEUTRAL": 0, "NEGATIVE": 0}, "shopping experience / delivery": {"POSITIVE": 0, "NEUTRAL": 0, "NEGATIVE": 0}}, "rating": 4.25}