{"asin": "B09G8Y4PZT", "name": "Apple iPhone 13 mini (128GB) - Pink", "ratings": [5, 5, 5, 5, 5, 1, 5, 5, 4, 5, 5, 4, 1, 3, 5, 4, 5, 5, 5, 4, 5, 5, 5, 5, 5, 5, 4, 4, 5, 5, 5, 5, 5, 5, 5, 5, 5, 5, 5, 1, 1, 5, 5, 5, 5, 5, 5, 5, 5, 5, 5, 5], "aspect_to_sentiments": {"overall": {"POSITIVE": 24, "NEUTRAL": 0, "NEGATIVE": 6}, "battery": {"POSITIVE": 4, "NEUTRAL": 0, "NEGATIVE": 0}, "camera": {"POSITIVE": 17, "NEUTRAL": 0, "NEGATIVE": 6}, "screen": {"POSITIVE": 16, "NEUTRAL": 0, "NEGATIVE": 12}, "value for price": {"POSITIVE": 10, "NEUTRAL": 0, "NEGATIVE": 1}, "service & warranty": {"POSITIVE": 6, "NEUTRAL": 1, "NEGATIVE": 7}, "brand & os": {"POSITIVE": 22, "NEUTRAL": 2, "NEGATIVE": 16}, "shopping experience / delivery": {"POSITIVE": 8, "NEUTRAL": 0, "NEGATIVE": 3}}, "rating": 4.54}